LICENSE.txt
MANIFEST.in
README.txt
setup.py
BuffetString.egg-info/PKG-INFO
BuffetString.egg-info/SOURCES.txt
BuffetString.egg-info/entry_points.txt
BuffetString.egg-info/not-zip-safe
BuffetString.egg-info/top_level.txt
buffetstring/__init__.py
buffetstring/stringsupport.py
test/templates/string_test.tmpl
