Metadata-Version: 1.0
Name: BuffetString
Version: 0.1.1
Summary: Python string Template plugin
Home-page: http://projects.dowski.com/projects/buffetstring
Author: Christian Wyglendowski
Author-email: christian@dowski.com
License: UNKNOWN
Platform: UNKNOWN
